paat/__init__.py
paat/calibration.py
paat/estimates.py
paat/features.py
paat/io.py
paat/models/TIB_model.pb/fingerprint.pb
paat/models/TIB_model.pb/keras_metadata.pb
paat/models/TIB_model.pb/saved_model.pb
paat/models/TIB_model.pb/variables/variables.data-00000-of-00001
paat/models/TIB_model.pb/variables/variables.index
paat/models/cnn_v2_10.pb/fingerprint.pb
paat/models/cnn_v2_10.pb/keras_metadata.pb
paat/models/cnn_v2_10.pb/saved_model.pb
paat/models/cnn_v2_10.pb/variables/variables.data-00000-of-00001
paat/models/cnn_v2_10.pb/variables/variables.index
paat/models/cnn_v2_2.pb/fingerprint.pb
paat/models/cnn_v2_2.pb/keras_metadata.pb
paat/models/cnn_v2_2.pb/saved_model.pb
paat/models/cnn_v2_2.pb/variables/variables.data-00000-of-00001
paat/models/cnn_v2_2.pb/variables/variables.index
paat/models/cnn_v2_3.pb/fingerprint.pb
paat/models/cnn_v2_3.pb/keras_metadata.pb
paat/models/cnn_v2_3.pb/saved_model.pb
paat/models/cnn_v2_3.pb/variables/variables.data-00000-of-00001
paat/models/cnn_v2_3.pb/variables/variables.index
paat/models/cnn_v2_4.pb/fingerprint.pb
paat/models/cnn_v2_4.pb/keras_metadata.pb
paat/models/cnn_v2_4.pb/saved_model.pb
paat/models/cnn_v2_4.pb/variables/variables.data-00000-of-00001
paat/models/cnn_v2_4.pb/variables/variables.index
paat/models/cnn_v2_5.pb/fingerprint.pb
paat/models/cnn_v2_5.pb/keras_metadata.pb
paat/models/cnn_v2_5.pb/saved_model.pb
paat/models/cnn_v2_5.pb/variables/variables.data-00000-of-00001
paat/models/cnn_v2_5.pb/variables/variables.index
paat/models/cnn_v2_6.pb/fingerprint.pb
paat/models/cnn_v2_6.pb/keras_metadata.pb
paat/models/cnn_v2_6.pb/saved_model.pb
paat/models/cnn_v2_6.pb/variables/variables.data-00000-of-00001
paat/models/cnn_v2_6.pb/variables/variables.index
paat/models/cnn_v2_7.pb/fingerprint.pb
paat/models/cnn_v2_7.pb/keras_metadata.pb
paat/models/cnn_v2_7.pb/saved_model.pb
paat/models/cnn_v2_7.pb/variables/variables.data-00000-of-00001
paat/models/cnn_v2_7.pb/variables/variables.index
paat-1.0.0.dist-info/LICENSE.txt
paat-1.0.0.dist-info/METADATA
paat-1.0.0.dist-info/WHEEL
paat-1.0.0.dist-info/RECORD
