Metadata-Version: 2.1
Name: paat
Version: 1.0.0
Summary: A comprehensive toolbox to analyse and model raw physical activity data
Home-page: https://github.com/Trybnetic/paat
License: MIT
Keywords: medical-informatics,physical-activity,health-science,actigraph,accelerometry
Author: Marc Weitz
Author-email: marc.weitz@uit.no
Requires-Python: >3.9,<3.13
Classifier: Development Status :: 4 - Beta
Classifier: Environment :: Console
Classifier: Intended Audience :: Science/Research
Classifier: License :: OSI Approved :: MIT License
Classifier: Operating System :: MacOS :: MacOS X
Classifier: Operating System :: Microsoft :: Windows
Classifier: Operating System :: POSIX
Classifier: Programming Language :: Python :: 3
Classifier: Programming Language :: Python :: 3.10
Classifier: Programming Language :: Python :: 3.11
Classifier: Programming Language :: Python :: 3.12
Provides-Extra: docs
Requires-Dist: agcounts (>=0.2,<0.3)
Requires-Dist: bitstring (>=3.1.7,<4.0.0)
Requires-Dist: glob2 (>=0.7,<0.8)
Requires-Dist: joblib (>=1.0.1,<2.0.0)
Requires-Dist: psutil (>=5.8.0,<6.0.0)
Requires-Dist: pygt3x (>=0.7.1,<0.8.0)
Requires-Dist: resampy (>=0,<1)
Requires-Dist: tables (>=3.7.0,<4.0.0)
Requires-Dist: tensorflow (>=2.16.1,<3.0.0)
Requires-Dist: toml (>=0.10.2,<0.11.0)
Project-URL: Repository, https://github.com/Trybnetic/paat
